panvimwiki/__init__.py
panvimwiki/catvimwiki.py
panvimwiki/convert.py
panvimwiki/vimwiki_week.py
panvimwiki/wiki2pandoc.py
panvimwiki/filter/__init__.py
panvimwiki/filter/delete_bullet_star.py
panvimwiki/filter/delete_empty_heading.py
panvimwiki/filter/delete_tag_lines.py
panvimwiki/filter/delete_task_pending.py
panvimwiki/filter/delete_taskwiki_heading.py
panvimwiki/filter/do_nothing.py
panvimwiki/filter/prefilter.py
panvimwiki/filter/reference_citation.py
panvimwiki/filter/wikilink_markdown.py
panvimwiki-0.11.0.dist-info/licenses/LICENSE.txt
panvimwiki-0.11.0.dist-info/METADATA
panvimwiki-0.11.0.dist-info/WHEEL
panvimwiki-0.11.0.dist-info/entry_points.txt
panvimwiki-0.11.0.dist-info/top_level.txt
panvimwiki-0.11.0.dist-info/RECORD
