Metadata-Version: 2.4
Name: panvimwiki
Version: 0.11.0
Summary: Filter and convert Vimwiki notes using pandoc.
Home-page: https://github.com/jfishe/panvimwiki
Author: John D. Fisher
Author-email: jdfenw@gmail.com
License: MIT
Project-URL: Documentation, https://panvimwiki.readthedocs.io/
Project-URL: Source, https://github.com/jfishe/panvimwiki
Project-URL: Tracker, https://github.com/jfishe/panvimwiki/issues
Project-URL: Changelog, https://panvimwiki.readthedocs.io/en/latest/changelog.html
Project-URL: Download, https://pypi.org/project/panvimwiki/#files
Keywords: panvimwiki,vimwiki,pandoc
Platform: any
Classifier: Development Status :: 4 - Beta
Classifier: Environment :: Console
Classifier: Intended Audience :: End Users/Desktop
Classifier: Natural Language :: English
Classifier: Programming Language :: Python
Classifier: Programming Language :: Python :: 3
Classifier: Programming Language :: Python :: 3.8
Classifier: Programming Language :: Python :: 3.9
Classifier: Programming Language :: Python :: 3.10
Classifier: Programming Language :: Python :: 3.11
Classifier: Programming Language :: Python :: 3.12
Classifier: Programming Language :: Python :: 3.13
Classifier: Programming Language :: Python :: Implementation :: CPython
Classifier: Topic :: Text Editors
Classifier: Topic :: Text Editors :: Text Processing
Requires-Python: >=3.8
License-File: LICENSE.txt
Requires-Dist: python-dateutil>=2.8
Requires-Dist: panflute
Requires-Dist: pypandoc
Requires-Dist: vim-bridge3
Requires-Dist: mdformat
Requires-Dist: mdformat-myst
Requires-Dist: mdformat-simple-breaks
Requires-Dist: mdformat-wikilink
Provides-Extra: testing
Requires-Dist: setuptools; extra == "testing"
Requires-Dist: pytest; extra == "testing"
Requires-Dist: pytest-cov; extra == "testing"
Requires-Dist: pytest-freezegun; extra == "testing"
Requires-Dist: pytest-pretty-terminal; extra == "testing"
Requires-Dist: python-dateutil>=2.8; extra == "testing"
Dynamic: license-file
